odoo/addons/project_risk/README.rst
odoo/addons/project_risk/__init__.py
odoo/addons/project_risk/__manifest__.py
odoo/addons/project_risk/data/project_risk_category_data.xml
odoo/addons/project_risk/data/project_risk_response_category_data.xml
odoo/addons/project_risk/i18n/es.po
odoo/addons/project_risk/i18n/it.po
odoo/addons/project_risk/i18n/project_risk.pot
odoo/addons/project_risk/i18n/sl.po
odoo/addons/project_risk/models/__init__.py
odoo/addons/project_risk/models/project_project.py
odoo/addons/project_risk/models/project_risk.py
odoo/addons/project_risk/models/project_risk_category.py
odoo/addons/project_risk/models/project_risk_response.py
odoo/addons/project_risk/models/project_risk_response_category.py
odoo/addons/project_risk/readme/CONFIGURE.rst
odoo/addons/project_risk/readme/CONTRIBUTORS.rst
odoo/addons/project_risk/readme/DESCRIPTION.rst
odoo/addons/project_risk/readme/ROADMAP.rst
odoo/addons/project_risk/readme/USAGE.rst
odoo/addons/project_risk/security/ir_model_access.xml
odoo/addons/project_risk/static/description/icon.png
odoo/addons/project_risk/static/description/index.html
odoo/addons/project_risk/static/description/matrix.png
odoo/addons/project_risk/tests/__init__.py
odoo/addons/project_risk/tests/test_project_risk.py
odoo/addons/project_risk/views/menuitems.xml
odoo/addons/project_risk/views/project_project_view.xml
odoo/addons/project_risk/views/project_risk_category_view.xml
odoo/addons/project_risk/views/project_risk_response_category_view.xml
odoo/addons/project_risk/views/project_risk_view.xml
odoo13_addon_project_risk-13.0.1.0.1.dev13.dist-info/METADATA
odoo13_addon_project_risk-13.0.1.0.1.dev13.dist-info/WHEEL
odoo13_addon_project_risk-13.0.1.0.1.dev13.dist-info/top_level.txt
odoo13_addon_project_risk-13.0.1.0.1.dev13.dist-info/RECORD
